{
  "$schema": "https://developer.microsoft.com/json-schemas/fabric/item/report/definition/visualContainer/1.6.0/schema.json",
  "name": "77d906124328ca38c4ed",
  "position": {
    "x": 876,
    "y": 119,
    "z": 3000,
    "height": 186,
    "width": 258,
    "tabOrder": 0
  },
  "visual": {
    "visualType": "cardVisual",
    "query": {
      "queryState": {
        "Data": {
          "projections": [
            {
              "field": {
                "Measure": {
                  "Expression": {
                    "SourceRef": {
                      "Entity": "FACT_ANSWERS"
                    }
                  },
                  "Property": "SommeID010"
                }
              },
              "queryRef": "FACT_ANSWERS.SommeID010",
              "nativeQueryRef": "SommeID010"
            }
          ]
        }
      },
      "sortDefinition": {
        "sort": [
          {
            "field": {
              "Measure": {
                "Expression": {
                  "SourceRef": {
                    "Entity": "FACT_ANSWERS"
                  }
                },
                "Property": "SommeID010"
              }
            },
            "direction": "Descending"
          }
        ],
        "isDefaultSort": true
      }
    },
    "drillFilterOtherVisuals": true
  }
}