{
  "$schema": "https://developer.microsoft.com/json-schemas/fabric/item/report/definition/visualContainer/1.6.0/schema.json",
  "name": "820ca60534993bd0da7a",
  "position": {
    "x": 448,
    "y": 104,
    "z": 5000,
    "height": 32,
    "width": 32,
    "tabOrder": 5000
  },
  "visual": {
    "visualType": "image",
    "objects": {
      "general": [
        {
          "properties": {
            "imageUrl": {
              "expr": {
                "ResourcePackageItem": {
                  "PackageName": "RegisteredResources",
                  "PackageType": 1,
                  "ItemName": "tracking5624722741674661.png"
                }
              }
            }
          }
        }
      ]
    },
    "drillFilterOtherVisuals": true
  },
  "howCreated": "InsertVisualButton"
}