{
  "$schema": "https://developer.microsoft.com/json-schemas/fabric/item/report/definition/visualContainer/1.6.0/schema.json",
  "name": "6fee97c4703c3e1a0609",
  "position": {
    "x": 256,
    "y": 288,
    "z": 14000,
    "height": 368,
    "width": 512,
    "tabOrder": 14000
  },
  "visual": {
    "visualType": "tableEx",
    "query": {
      "queryState": {
        "Values": {
          "projections": [
            {
              "field": {
                "Column": {
                  "Expression": {
                    "SourceRef": {
                      "Entity": "COUNTRY"
                    }
                  },
                  "Property": "SURNAME"
                }
              },
              "queryRef": "COUNTRY.SURNAME",
              "nativeQueryRef": "Country",
              "displayName": "Country"
            },
            {
              "field": {
                "Measure": {
                  "Expression": {
                    "SourceRef": {
                      "Entity": "FACT_ANSWERS"
                    }
                  },
                  "Property": "Nombre Secondary activity"
                }
              },
              "queryRef": "FACT_ANSWERS.Nombre Secondary activity",
              "nativeQueryRef": "Nombre Secondary activity"
            },
            {
              "field": {
                "Measure": {
                  "Expression": {
                    "SourceRef": {
                      "Entity": "FACT_ANSWERS"
                    }
                  },
                  "Property": "Proportion Secondary Activity"
                }
              },
              "queryRef": "FACT_ANSWERS.Proportion Secondary Activity",
              "nativeQueryRef": "Proportion Secondary Activity"
            }
          ]
        }
      },
      "sortDefinition": {
        "sort": [
          {
            "field": {
              "Column": {
                "Expression": {
                  "SourceRef": {
                    "Entity": "COUNTRY"
                  }
                },
                "Property": "SURNAME"
              }
            },
            "direction": "Ascending"
          }
        ],
        "isDefaultSort": true
      }
    },
    "objects": {
      "columnWidth": [
        {
          "properties": {
            "value": {
              "expr": {
                "Literal": {
                  "Value": "110.72906005495462D"
                }
              }
            }
          },
          "selector": {
            "metadata": "COUNTRY.SURNAME"
          }
        }
      ],
      "total": [
        {
          "properties": {
            "backColor": {
              "solid": {
                "color": {
                  "expr": {
                    "Literal": {
                      "Value": "'#094780'"
                    }
                  }
                }
              }
            },
            "fontColor": {
              "solid": {
                "color": {
                  "expr": {
                    "ThemeDataColor": {
                      "ColorId": 0,
                      "Percent": 0
                    }
                  }
                }
              }
            },
            "bold": {
              "expr": {
                "Literal": {
                  "Value": "true"
                }
              }
            }
          }
        }
      ],
      "columnHeaders": [
        {
          "properties": {
            "fontColor": {
              "solid": {
                "color": {
                  "expr": {
                    "ThemeDataColor": {
                      "ColorId": 0,
                      "Percent": 0
                    }
                  }
                }
              }
            },
            "bold": {
              "expr": {
                "Literal": {
                  "Value": "true"
                }
              }
            },
            "backColor": {
              "solid": {
                "color": {
                  "expr": {
                    "Literal": {
                      "Value": "'#094780'"
                    }
                  }
                }
              }
            }
          }
        }
      ]
    },
    "visualContainerObjects": {
      "title": [
        {
          "properties": {
            "text": {
              "expr": {
                "Literal": {
                  "Value": "'Table Secondary Activity'"
                }
              }
            }
          }
        }
      ]
    },
    "drillFilterOtherVisuals": true
  },
  "filterConfig": {
    "filters": [
      {
        "name": "fb1102230f20612b036f",
        "field": {
          "Column": {
            "Expression": {
              "SourceRef": {
                "Entity": "QUESTION"
              }
            },
            "Property": "CODE"
          }
        },
        "type": "Categorical",
        "filter": {
          "Version": 2,
          "From": [
            {
              "Name": "q",
              "Entity": "QUESTION",
              "Type": 0
            }
          ],
          "Where": [
            {
              "Condition": {
                "In": {
                  "Expressions": [
                    {
                      "Column": {
                        "Expression": {
                          "SourceRef": {
                            "Source": "q"
                          }
                        },
                        "Property": "CODE"
                      }
                    }
                  ],
                  "Values": [
                    [
                      {
                        "Literal": {
                          "Value": "'ID.004'"
                        }
                      }
                    ],
                    [
                      {
                        "Literal": {
                          "Value": "'ID.005'"
                        }
                      }
                    ],
                    [
                      {
                        "Literal": {
                          "Value": "'ID.006'"
                        }
                      }
                    ],
                    [
                      {
                        "Literal": {
                          "Value": "'ID.009'"
                        }
                      }
                    ],
                    [
                      {
                        "Literal": {
                          "Value": "'ID.019'"
                        }
                      }
                    ],
                    [
                      {
                        "Literal": {
                          "Value": "'ID.020'"
                        }
                      }
                    ],
                    [
                      {
                        "Literal": {
                          "Value": "'ID.021'"
                        }
                      }
                    ],
                    [
                      {
                        "Literal": {
                          "Value": "'ID.022'"
                        }
                      }
                    ],
                    [
                      {
                        "Literal": {
                          "Value": "'ID.023'"
                        }
                      }
                    ],
                    [
                      {
                        "Literal": {
                          "Value": "'ID.024'"
                        }
                      }
                    ],
                    [
                      {
                        "Literal": {
                          "Value": "'ID.025'"
                        }
                      }
                    ],
                    [
                      {
                        "Literal": {
                          "Value": "'ID.026'"
                        }
                      }
                    ],
                    [
                      {
                        "Literal": {
                          "Value": "'ID.027'"
                        }
                      }
                    ],
                    [
                      {
                        "Literal": {
                          "Value": "'ID.028'"
                        }
                      }
                    ],
                    [
                      {
                        "Literal": {
                          "Value": "'ID.029'"
                        }
                      }
                    ]
                  ]
                }
              }
            }
          ]
        },
        "howCreated": "User",
        "objects": {
          "general": [
            {
              "properties": {}
            }
          ]
        }
      }
    ]
  },
  "isHidden": true
}